walytis_beta_api/__init__.py
walytis_beta_api/__main__.py
walytis_beta_api/__project__.py
walytis_beta_api/block_model.py
walytis_beta_api/blockchain_model.py
walytis_beta_api/exceptions.py
walytis_beta_api/versions.py
walytis_beta_api/walytis_beta_interface.py
walytis_api-0.0.0.dist-info/METADATA
walytis_api-0.0.0.dist-info/WHEEL
walytis_api-0.0.0.dist-info/top_level.txt
walytis_api-0.0.0.dist-info/RECORD
