Metadata-Version: 2.1
Name: walytis_api
Version: 0.0.0
Summary: A library for interacting with Walytis_Beta: a lightweight, flexible, non-linear blockchain.
Home-page: https://ipfs.io/ipns/k2k4r8nismm5mmgrox2fci816xvj4l4cudnuc55gkfoealjuiaexbsup/Sites/BrenthyAndWalytis_Beta/Documentation/Walytis/Meaning/Introduction.md.html
Author: emendir
Project-URL: Github, https://github.com/emendir/Brenthy
Classifier: Programming Language :: Python :: 3
Classifier: Operating System :: OS Independent
Requires-Python: >=3.6
Requires-Dist: appdirs ==1.4.3
Requires-Dist: ipfs-toolkit >=0.5.19
Requires-Dist: pyzmq ==25.1.1
Requires-Dist: brenthy-tools-beta
